familytree/LouisXIVfamily.svg
familytree/LouisXIVfamily.txt
familytree/README.md
familytree/__init__.py
familytree/familytreemaker.py
familytree-0.0.11.dist-info/LICENSE
familytree-0.0.11.dist-info/METADATA
familytree-0.0.11.dist-info/WHEEL
familytree-0.0.11.dist-info/top_level.txt
familytree-0.0.11.dist-info/RECORD
