Metadata-Version: 2.1
Name: familytree
Version: 0.0.11
Summary: This program creates family tree graphs from a simple text files
Home-page: https://github.com/tjnh05/familytreemaker
Author: Bodhi Wang
Author-email: jyxz5@hotmail.com
License: MIT
Keywords: familytree familytreemaker
Platform: any
Classifier: Programming Language :: Python :: 3
Classifier: License :: OSI Approved :: MIT License
Classifier: Operating System :: OS Independent
Requires-Python: >=3.5
